<annotation><folder>open_images_volume</folder><filename>Bicycle_0d38487b98a16d31.jpg</filename><path>/mnt/open_images_volume/Bicycle_0d38487b98a16d31.jpg</path><source><database>Unknown</database></source><size><width>1024</width><height>768</height><depth>3</depth></size><segmented>0</segmented><object><name>Bicycle</name><pose>Unspecified</pose><truncated>0</truncated><difficult>0</difficult><bndbox><xmin>66</xmin><ymin>161</ymin><xmax>617</xmax><ymax>547</ymax></bndbox></object><object><name>Bicycle</name><pose>Unspecified</pose><truncated>0</truncated><difficult>0</difficult><bndbox><xmin>117</xmin><ymin>35</ymin><xmax>178</xmax><ymax>95</ymax></bndbox></object><object><name>Bicycle</name><pose>Unspecified</pose><truncated>0</truncated><difficult>0</difficult><bndbox><xmin>129</xmin><ymin>95</ymin><xmax>469</xmax><ymax>296</ymax></bndbox></object><object><name>Bicycle</name><pose>Unspecified</pose><truncated>0</truncated><difficult>0</difficult><bndbox><xmin>133</xmin><ymin>123</ymin><xmax>461</xmax><ymax>313</ymax></bndbox></object></annotation>